bumpkin/VERSION
bumpkin/__init__.py
bumpkin/__main__.py
bumpkin/base.py
bumpkin/cli.py
bumpkin/sources/__init__.py
bumpkin/sources/__main__.py
bumpkin/sources/base.py
bumpkin/sources/default.nix
bumpkin/sources/basicgithub/__init__.py
bumpkin/sources/basicgithub/default.nix
bumpkin/sources/basichttp/__init__.py
bumpkin/sources/basichttp/default.nix
bumpkin/sources/basichttpjsonvendor/__init__.py
bumpkin/sources/basichttpjsonvendor/default.nix
bumpkin-0.1.0.dist-info/METADATA
bumpkin-0.1.0.dist-info/WHEEL
bumpkin-0.1.0.dist-info/entry_points.txt
bumpkin-0.1.0.dist-info/licenses/LICENSE
bumpkin-0.1.0.dist-info/RECORD
