Metadata-Version: 2.4
Name: bumpkin
Version: 0.1.0
Summary: Tool to do source bumps
License-File: LICENSE
